README.md
setup.cfg
setup.py
theia_open/__init__.py
theia_open/__main__.py
theia_open/cli.py
theia_open.egg-info/PKG-INFO
theia_open.egg-info/SOURCES.txt
theia_open.egg-info/dependency_links.txt
theia_open.egg-info/entry_points.txt
theia_open.egg-info/requires.txt
theia_open.egg-info/top_level.txt