Metadata-Version: 2.1
Name: theia-open
Version: 0.2.0
Summary: A command line to open file from within theia
Home-page: https://github.com/perrinjerome/theia-open/
License: UNKNOWN
Keywords: theia editor
Platform: UNKNOWN
Classifier: Intended Audience :: Developers
Classifier: Topic :: Software Development
Classifier: License :: OSI Approved :: MIT License
Classifier: Programming Language :: Python :: 3
Requires-Python: >=3.6.*
